maec/__init__.py
maec/version.py
maec/analytics/__init__.py
maec/analytics/distance.py
maec/analytics/static_features.py
maec/bindings/__init__.py
maec/bindings/maec_bundle.py
maec/bindings/maec_container.py
maec/bindings/maec_package.py
maec/bindings/mmdef_1_2.py
maec/bundle/__init__.py
maec/bundle/action_reference_list.py
maec/bundle/av_classification.py
maec/bundle/behavior.py
maec/bundle/behavior_reference.py
maec/bundle/bundle.py
maec/bundle/bundle_reference.py
maec/bundle/candidate_indicator.py
maec/bundle/capability.py
maec/bundle/malware_action.py
maec/bundle/object_history.py
maec/bundle/object_reference.py
maec/bundle/process_tree.py
maec/misc/__init__.py
maec/misc/exceptions.py
maec/misc/options.py
maec/package/__init__.py
maec/package/action_equivalence.py
maec/package/analysis.py
maec/package/grouping_relationship.py
maec/package/malware_subject.py
maec/package/malware_subject_reference.py
maec/package/object_equivalence.py
maec/package/package.py
maec/test/__init__.py
maec/test/encoding_test.py
maec/test/bundle/__init__.py
maec/test/bundle/av_classification_test.py
maec/test/bundle/behavior_test.py
maec/test/bundle/bundle_test.py
maec/test/bundle/capability_test.py
maec/test/bundle/process_tree_test.py
maec/test/package/__init__.py
maec/test/package/analysis_test.py
maec/test/package/malware_subject_test.py
maec/test/package/package_test.py
maec/test/utils/__init__.py
maec/test/utils/nsparser_test.py
maec/test/utils/parser_test.py
maec/utils/__init__.py
maec/utils/comparator.py
maec/utils/deduplicator.py
maec/utils/merge.py
maec/utils/nsparser.py
maec/utils/parser.py
maec/vocabs/__init__.py
maec/vocabs/vocabs.py
maec-4.1.0.17.dist-info/LICENSE.txt
maec-4.1.0.17.dist-info/METADATA
maec-4.1.0.17.dist-info/WHEEL
maec-4.1.0.17.dist-info/top_level.txt
maec-4.1.0.17.dist-info/RECORD
