Metadata-Version: 2.1
Name: maec
Version: 4.1.0.17
Summary: An API for parsing and creating MAEC content.
Home-page: https://maecproject.github.io/
Author: MAEC Project
Author-email: maec@mitre.org
License: BSD
Project-URL: Source Code, https://github.com/MAECProject/python-maec/
Project-URL: Documentation, https://maec.readthedocs.io/
Project-URL: Bug Tracker, https://github.com/MAECProject/python-maec/issues/
Platform: UNKNOWN
Classifier: Programming Language :: Python :: 2
Classifier: Programming Language :: Python :: 2.7
Classifier: Programming Language :: Python :: 3
Classifier: Programming Language :: Python :: 3.4
Classifier: Programming Language :: Python :: 3.5
Classifier: Programming Language :: Python :: 3.6
Classifier: Programming Language :: Python :: 3.7
Classifier: Programming Language :: Python :: 3.8
Classifier: Development Status :: 4 - Beta
Classifier: Intended Audience :: Developers
Classifier: License :: OSI Approved :: BSD License
Classifier: Operating System :: OS Independent
Provides-Extra: test
Provides-Extra: docs
